mikro_next/__init__.py
mikro_next/arkitekt.py
mikro_next/datalayer.py
mikro_next/errors.py
mikro_next/funcs.py
mikro_next/mikro_next.py
mikro_next/rath.py
mikro_next/rekuest.py
mikro_next/scalars.py
mikro_next/traits.py
mikro_next/utils.py
mikro_next/widgets.py
mikro_next/api/__init__.py
mikro_next/api/project.json
mikro_next/api/schema.graphql
mikro_next/api/schema.py
mikro_next/contrib/__init__.py
mikro_next/contrib/fakts/__init__.py
mikro_next/contrib/fakts/datalayer.py
mikro_next/deployments/test/docker-compose.yml
mikro_next/deployments/test/public_key.pem
mikro_next/deployments/test/configs/mikro_next.yaml
mikro_next/deployments/test/configs/minio.yaml
mikro_next/io/__init__.py
mikro_next/io/download.py
mikro_next/io/errors.py
mikro_next/io/types.py
mikro_next/io/upload.py
mikro_next/links/__init__.py
mikro_next/links/errors.py
mikro_next/links/upload.py
mikro_next-0.19.0.dist-info/METADATA
mikro_next-0.19.0.dist-info/WHEEL
mikro_next-0.19.0.dist-info/RECORD
