Metadata-Version: 2.4
Name: mikro-next
Version: 0.19.0
Summary: next images for arkitekt
Author-email: jhnnsrs <jhnnsrs@gmail.com>
License-Expression: MIT
Requires-Python: >=3.11
Requires-Dist: dask>=2024.12.1
Requires-Dist: fakts-next>=2
Requires-Dist: numcodecs>=0.16.1
Requires-Dist: numpy>=1.26; python_version ~= '3.12'
Requires-Dist: pandas>=2.2
Requires-Dist: pytest>=8.3.5
Requires-Dist: rath>=3.7
Requires-Dist: s3fs>=2024.10.0
Requires-Dist: websockets>=15.0.1
Requires-Dist: xarray>=2024.11.0
Requires-Dist: zarr>=3.1
Provides-Extra: complete
Requires-Dist: pyarrow>=12.0.1; extra == 'complete'
Provides-Extra: table
Requires-Dist: pyarrow>=12.0.1; extra == 'table'
Provides-Extra: turms
